.dockerignore
.gitignore
.pre-commit-config.yaml
CHANGELOG.rst
CONTRIBUTING.md
Dockerfile
LICENSE
README.rst
compile-requirements.sh
config.toml
constraints.in
dev-requirements.in
dev-requirements.txt
pyproject.toml
pytest
requirements.txt
setup.cfg
setup.py
tox.ini
.circleci/config.yml
.dependabot/config.yml
config/addresses_laika.json
config/addresses_tlbc.json
docker/trustlines/.env
docker/trustlines/.gitignore
docker/trustlines/README.md
docker/trustlines/config.toml
docker/trustlines/tlbc/.env
docker/trustlines/tlbc/config.dist.toml
docker/trustlines/tlbc/docker-compose.yml
docker/trustlines/tlbc/node-config.dist.toml
src/relay/__init__.py
src/relay/boot.py
src/relay/concurrency_utils.py
src/relay/constants.py
src/relay/events.py
src/relay/main.py
src/relay/relay.py
src/relay/signing.py
src/relay/signing_middleware.py
src/relay/streams.py
src/relay/utils.py
src/relay/web3provider.py
src/relay/api/__init__.py
src/relay/api/app.py
src/relay/api/fields.py
src/relay/api/resources.py
src/relay/api/schemas.py
src/relay/api/exchange/__init__.py
src/relay/api/exchange/resources.py
src/relay/api/exchange/schemas.py
src/relay/api/messaging/__init__.py
src/relay/api/messaging/resources.py
src/relay/api/pushservice/__init__.py
src/relay/api/pushservice/resources.py
src/relay/api/streams/__init__.py
src/relay/api/streams/app.py
src/relay/api/streams/rpc_methods.py
src/relay/api/streams/rpc_protocol.py
src/relay/api/streams/transport.py
src/relay/api/tokens/__init__.py
src/relay/api/tokens/resources.py
src/relay/blockchain/__init__.py
src/relay/blockchain/currency_network_events.py
src/relay/blockchain/currency_network_proxy.py
src/relay/blockchain/delegate.py
src/relay/blockchain/events.py
src/relay/blockchain/exchange_events.py
src/relay/blockchain/exchange_proxy.py
src/relay/blockchain/identity_events.py
src/relay/blockchain/identity_proxy.py
src/relay/blockchain/node.py
src/relay/blockchain/proxy.py
src/relay/blockchain/token_events.py
src/trustlines_relay.egg-info/PKG-INFO
src/trustlines_relay.egg-info/SOURCES.txt
src/trustlines_relay.egg-info/dependency_links.txt
src/trustlines_relay.egg-info/entry_points.txt
src/trustlines_relay.egg-info/requires.txt
src/trustlines_relay.egg-info/top_level.txt
