Metadata-Version: 1.2
Name: trustlines-relay
Version: 0.23.0
Summary: Relay Server for the Trustlines Network
Home-page: https://github.com/trustlines-protocol/relay
Author: Trustlines-Network
Author-email: contact@brainbot.com
License: MIT
Keywords: trustlines
Platform: UNKNOWN
Classifier: Development Status :: 2 - Pre-Alpha
Classifier: Intended Audience :: Developers
Classifier: License :: OSI Approved :: MIT License
Classifier: Programming Language :: Python :: 3
Classifier: Programming Language :: Python :: 3.6
Classifier: Programming Language :: Python :: 3.7
Classifier: Programming Language :: Python :: 3.8
Classifier: Programming Language :: Python :: 3.9
Requires-Python: >=3.6
